flask_tsk-2.0.4.dist-info/licenses/LICENSE
tsk_flask/__init__.py
tsk_flask/blueprint.py
tsk_flask/cli.py
tsk_flask/component_example.py
tsk_flask/database.py
tsk_flask/elephant_routes.py
tsk_flask/elephant_showcase.py
tsk_flask/elephants.py
tsk_flask/example_runner.py
tsk_flask/fastapi_routes.py
tsk_flask/memory.py
tsk_flask/optimization_tools.py
tsk_flask/performance_benchmark.py
tsk_flask/performance_demo.py
tsk_flask/performance_engine.py
tsk_flask/theme_components.py
tsk_flask/theme_config.py
tsk_flask/theme_showcase.py
tsk_flask/themes.py
tsk_flask/ascii_art/__init__.py
tsk_flask/ascii_art/ascii/alert.txt
tsk_flask/ascii_art/ascii/box.txt
tsk_flask/ascii_art/ascii/circus.txt
tsk_flask/ascii_art/ascii/create.txt
tsk_flask/ascii_art/ascii/cron.txt
tsk_flask/ascii_art/ascii/css.txt
tsk_flask/ascii_art/ascii/dumbo.txt
tsk_flask/ascii_art/ascii/elder.txt
tsk_flask/ascii_art/ascii/ele-1.txt
tsk_flask/ascii_art/ascii/eli.txt
tsk_flask/ascii_art/ascii/happy.txt
tsk_flask/ascii_art/ascii/heard.txt
tsk_flask/ascii_art/ascii/horton.txt
tsk_flask/ascii_art/ascii/koshik.txt
tsk_flask/ascii_art/ascii/loading.txt
tsk_flask/ascii_art/ascii/love.txt
tsk_flask/ascii_art/ascii/peace.txt
tsk_flask/ascii_art/ascii/peanut-alt.txt
tsk_flask/ascii_art/ascii/peanut.txt
tsk_flask/ascii_art/ascii/shit.txt
tsk_flask/ascii_art/ascii/squirt.txt
tsk_flask/ascii_art/ascii/turd-sm.txt
tsk_flask/ascii_art/ascii/turd.txt
tsk_flask/ascii_art/ascii/tusk.txt
tsk_flask/components/__init__.py
tsk_flask/components/blog.py
tsk_flask/components/ecommerce.py
tsk_flask/components/forms.py
tsk_flask/components/layouts.py
tsk_flask/components/navigation.py
tsk_flask/components/ui.py
tsk_flask/database_templates/__init__.py
tsk_flask/database_templates/elephant_services.sql
tsk_flask/database_templates/herd_auth.sql
tsk_flask/examples/__init__.py
tsk_flask/examples/api_service.py
tsk_flask/examples/base_example.py
tsk_flask/examples/basic_auth.py
tsk_flask/examples/blog_system.py
tsk_flask/examples/dashboard.py
tsk_flask/examples/ecommerce.py
flask_tsk-2.0.4.dist-info/METADATA
flask_tsk-2.0.4.dist-info/WHEEL
flask_tsk-2.0.4.dist-info/top_level.txt
flask_tsk-2.0.4.dist-info/RECORD
