Metadata-Version: 2.4
Name: flask-tsk
Version: 2.0.4
Summary: Flask Extension for TuskLang Integration - Up to 59x Faster Template Rendering (Verified)
Home-page: https://github.com/grim-project/flask-tsk
Author: Grim Development Team
Author-email: Grim Development Team <grim@example.com>
Maintainer-email: Grim Development Team <grim@example.com>
License: MIT
Project-URL: Homepage, https://github.com/grim-project/flask-tsk
Project-URL: Documentation, https://flask-tsk.readthedocs.io/
Project-URL: Repository, https://github.com/grim-project/flask-tsk
Project-URL: Bug Tracker, https://github.com/grim-project/flask-tsk/issues
Project-URL: Performance Guide, https://github.com/grim-project/flask-tsk/blob/main/PERFORMANCE_REVOLUTION.md
Keywords: flask,tusk,tusktsk,configuration,performance,template-engine
Platform: any
Classifier: Development Status :: 4 - Beta
Classifier: Environment :: Web Environment
Classifier: Framework :: Flask
Classifier: Intended Audience :: Developers
Classifier: License :: OSI Approved :: MIT License
Classifier: Operating System :: OS Independent
Classifier: Programming Language :: Python :: 3
Classifier: Programming Language :: Python :: 3.8
Classifier: Programming Language :: Python :: 3.9
Classifier: Programming Language :: Python :: 3.10
Classifier: Programming Language :: Python :: 3.11
Classifier: Programming Language :: Python :: 3.12
Classifier: Topic :: Internet :: WWW/HTTP :: Dynamic Content
Classifier: Topic :: Software Development :: Libraries :: Python Modules
Classifier: Topic :: System :: Systems Administration
Requires-Python: >=3.8
License-File: LICENSE
Requires-Dist: Flask>=2.0.0
Requires-Dist: tusktsk>=2.0.4
Provides-Extra: dev
Requires-Dist: pytest>=7.0.0; extra == "dev"
Requires-Dist: pytest-cov>=4.0.0; extra == "dev"
Requires-Dist: pytest-flask>=1.2.0; extra == "dev"
Requires-Dist: black>=22.0.0; extra == "dev"
Requires-Dist: flake8>=4.0.0; extra == "dev"
Requires-Dist: mypy>=0.950; extra == "dev"
Provides-Extra: databases
Requires-Dist: psycopg2-binary>=2.9.0; extra == "databases"
Requires-Dist: pymongo>=4.0.0; extra == "databases"
Requires-Dist: redis>=5.0.0; extra == "databases"
Provides-Extra: performance
Requires-Dist: orjson>=3.0.0; extra == "performance"
Requires-Dist: ujson>=5.0.0; extra == "performance"
Requires-Dist: msgpack>=1.0.0; extra == "performance"
Provides-Extra: fastapi
Requires-Dist: fastapi>=0.104.1; extra == "fastapi"
Requires-Dist: uvicorn[standard]>=0.24.0; extra == "fastapi"
Requires-Dist: pydantic>=2.5.0; extra == "fastapi"
Dynamic: author
Dynamic: home-page
Dynamic: license-file
Dynamic: platform
Dynamic: requires-python
